tsnkit/__init__.py
tsnkit/algorithms/__init__.py
tsnkit/algorithms/at.py
tsnkit/algorithms/cg.py
tsnkit/algorithms/cp_wa.py
tsnkit/algorithms/dt.py
tsnkit/algorithms/i_ilp.py
tsnkit/algorithms/i_omt.py
tsnkit/algorithms/jrs_mc.py
tsnkit/algorithms/jrs_nw.py
tsnkit/algorithms/jrs_nw_l.py
tsnkit/algorithms/jrs_wa.py
tsnkit/algorithms/ls.py
tsnkit/algorithms/ls_pl.py
tsnkit/algorithms/ls_tb.py
tsnkit/algorithms/smt_fr.py
tsnkit/algorithms/smt_nw.py
tsnkit/algorithms/smt_pr.py
tsnkit/algorithms/smt_wa.py
tsnkit/core/__init__.py
tsnkit/core/_calculate.py
tsnkit/core/_common.py
tsnkit/core/_config.py
tsnkit/core/_constants.py
tsnkit/core/_io.py
tsnkit/core/_network.py
tsnkit/core/_stream.py
tsnkit/core/_system.py
tsnkit/data/__init__.py
tsnkit/data/dataset_spec.py
tsnkit/data/generator.py
tsnkit/simulation/__init__.py
tsnkit/simulation/draw.py
tsnkit/simulation/tas.py
tsnkit/simulation/cython/__init__.py
tsnkit/simulation/cython/simulation_core.c
tsnkit/simulation/cython/simulation_core.cpython-311-darwin.so
tsnkit/simulation/cython/simulation_core.pyx
tsnkit/test/__init__.py
tsnkit/test/benchmark/__init__.py
tsnkit/test/benchmark/__main__.py
tsnkit/test/benchmark/_processes.py
tsnkit/test/benchmark/draw.py
tsnkit/test/debug/__init__.py
tsnkit/test/debug/__main__.py
tsnkit/test/debug/_common.py
tsnkit/test/debug/_validate_classes.py
tsnkit/test/debug/_validate_io.py
tsnkit/test/debug/_validate_simulator.py
tsnkit/test/debug/at.py
tsnkit/test/debug/cg.py
tsnkit/test/debug/cp_wa.py
tsnkit/test/debug/dt.py
tsnkit/test/debug/i_ilp.py
tsnkit/test/debug/i_omt.py
tsnkit/test/debug/jrs_mc.py
tsnkit/test/debug/jrs_nw.py
tsnkit/test/debug/jrs_nw_l.py
tsnkit/test/debug/jrs_wa.py
tsnkit/test/debug/ls.py
tsnkit/test/debug/ls_pl.py
tsnkit/test/debug/ls_tb.py
tsnkit/test/debug/smt_fr.py
tsnkit/test/debug/smt_nw.py
tsnkit/test/debug/smt_pr.py
tsnkit/test/debug/smt_wa.py
tsnkit-0.3.0.dist-info/licenses/LICENSE
tsnkit-0.3.0.dist-info/METADATA
tsnkit-0.3.0.dist-info/WHEEL
tsnkit-0.3.0.dist-info/top_level.txt
tsnkit-0.3.0.dist-info/RECORD
