Metadata-Version: 2.4
Name: tsnkit
Version: 0.3.0
Summary: A simple scheduling toolkit for time-sensitive network in Python.
Author-email: Chuanyu Xue <skewcy@gmail.com>, Elaine Hu <elainehu222@gmail.com>
Project-URL: Homepage, https://github.com/ChuanyuXue/tsnkit
Project-URL: Bug Tracker, https://github.com/ChuanyuXue/tsnkit
Classifier: Programming Language :: Python :: 3
Classifier: Development Status :: 3 - Alpha
Classifier: Intended Audience :: Science/Research
Classifier: License :: OSI Approved :: MIT License
Requires-Python: >=3.9
License-File: LICENSE
Requires-Dist: z3-solver>=4.11.2
Requires-Dist: docplex>=2.23.222
Requires-Dist: gurobipy>=9.5.1
Requires-Dist: networkx>=2.8.8
Requires-Dist: numpy>=1.21.4
Requires-Dist: pandas>=1.4.1
Requires-Dist: psutil>=5.9.4
Requires-Dist: tqdm>=4.62.0
Dynamic: license-file
